timeatlas/__init__.py
timeatlas/abstract/__init__.py
timeatlas/abstract/abstract_base_detector.py
timeatlas/abstract/abstract_base_generator.py
timeatlas/abstract/abstract_base_model.py
timeatlas/abstract/abstract_base_time_series.py
timeatlas/abstract/abstract_base_types.py
timeatlas/abstract/abstract_io.py
timeatlas/config/__init__.py
timeatlas/config/colors.py
timeatlas/config/constants.py
timeatlas/detectors/__init__.py
timeatlas/detectors/surprise.py
timeatlas/generators/__init__.py
timeatlas/generators/anomaly_generator/__init__.py
timeatlas/generators/anomaly_generator/anomaly_generator.py
timeatlas/generators/anomaly_generator/utils.py
timeatlas/generators/anomaly_generator/anomalies/__init__.py
timeatlas/generators/anomaly_generator/anomalies/anomalies.py
timeatlas/generators/anomaly_generator/anomalies/utils.py
timeatlas/generators/anomaly_generator/config/__init__.py
timeatlas/generators/anomaly_generator/config/validate_configfile.py
timeatlas/generators/anomaly_generator/config/write_template.py
timeatlas/generators/anomaly_generator/labeler/__init__.py
timeatlas/generators/anomaly_generator/labeler/labeler.py
timeatlas/metadata/__init__.py
timeatlas/metadata/metadata.py
timeatlas/metrics/__init__.py
timeatlas/metrics/pairwise.py
timeatlas/models/__init__.py
timeatlas/models/linear_regression.py
timeatlas/models/lstm.py
timeatlas/models/prophet.py
timeatlas/models/NN/__init__.py
timeatlas/models/NN/util.py
timeatlas/models/NN/dataloader/__init__.py
timeatlas/models/NN/dataloader/base_dataloader.py
timeatlas/models/NN/dataloader/prediction_dataloader.py
timeatlas/models/NN/dataset/__init__.py
timeatlas/models/NN/dataset/base_dataset.py
timeatlas/models/NN/dataset/classification_dataset.py
timeatlas/models/NN/dataset/prediction_dataset.py
timeatlas/models/NN/models/__init__.py
timeatlas/plots/__init__.py
timeatlas/plots/_utils.py
timeatlas/plots/time_series.py
timeatlas/plots/time_series_dataset.py
timeatlas/processors/__init__.py
timeatlas-0.1.1.dist-info/LICENSE
timeatlas-0.1.1.dist-info/METADATA
timeatlas-0.1.1.dist-info/WHEEL
timeatlas-0.1.1.dist-info/top_level.txt
timeatlas-0.1.1.dist-info/RECORD
