Metadata-Version: 2.1
Name: timeatlas
Version: 0.1.1
Summary: A time series data manipulation tool for Python
Home-page: UNKNOWN
Author: Frédéric Montet
Author-email: frederic.montet@hefr.ch
License: UNKNOWN
Platform: UNKNOWN
Classifier: Programming Language :: Python :: 3
Classifier: License :: OSI Approved :: MIT License
Classifier: Operating System :: OS Independent
Requires-Python: >=3.7
Requires-Dist: configobj (==5.*)
Requires-Dist: matplotlib (==3.*)
Requires-Dist: pandas (==1.*)
Requires-Dist: seaborn (==0.*)
Requires-Dist: scipy (==1.*)
Requires-Dist: u8darts (==0.*)
Requires-Dist: plotly (==4.*)
Provides-Extra: all
Requires-Dist: configobj (==5.*) ; extra == 'all'
Requires-Dist: matplotlib (==3.*) ; extra == 'all'
Requires-Dist: pandas (==1.*) ; extra == 'all'
Requires-Dist: seaborn (==0.*) ; extra == 'all'
Requires-Dist: scipy (==1.*) ; extra == 'all'
Requires-Dist: u8darts (==0.*) ; extra == 'all'
Requires-Dist: plotly (==4.*) ; extra == 'all'
Requires-Dist: fbprophet (==0.*) ; extra == 'all'
Requires-Dist: torch (==1.6.*) ; extra == 'all'
Provides-Extra: prophet
Requires-Dist: fbprophet (==0.*) ; extra == 'prophet'
Provides-Extra: torch
Requires-Dist: torch (==1.6.*) ; extra == 'torch'
